gardener_ci/VERSION
gardener_ci/__init__.py
gardener_ci/_concourse.py
gardener_ci/_cosign.py
gardener_ci/_oci.py
gardener_ci/_ocm.py
gardener_ci/_release_notes.py
gardener_ci/_slack.py
gardener_ci/cd.py
gardener_ci/cli_gen.py
gardener_ci/compliance.py
gardener_ci/config.py
gardener_ci/containerutil.py
gardener_ci/docker.py
gardener_ci/gh.py
gardener_ci/githubutil.py
gardener_ci/pipeline.py
gardener_ci/productutil_v2.py
gardener_ci/sign.py
gardener_ci/yaml2json.py
gardener_cicd_cli-1.2740.0.data/scripts/purge_history
gardener_cicd_cli-1.2740.0.dist-info/METADATA
gardener_cicd_cli-1.2740.0.dist-info/WHEEL
gardener_cicd_cli-1.2740.0.dist-info/entry_points.txt
gardener_cicd_cli-1.2740.0.dist-info/top_level.txt
gardener_cicd_cli-1.2740.0.dist-info/RECORD
