Metadata-Version: 2.1
Name: gardener-cicd-cli
Version: 1.2740.0
Summary: Gardener CI/CD Command Line Interface
Requires-Python: >=3.11
Requires-Dist: gardener-cicd-libs ==1.2740.0
